HISTORY.rst
LICENSE
MANIFEST.in
README.rst
setup.py
pyflix2/__init__.py
pyflix2/__main__.py
pyflix2/pyflix2.py
pyflix2/test.py
pyflix2.egg-info/PKG-INFO
pyflix2.egg-info/SOURCES.txt
pyflix2.egg-info/dependency_links.txt
pyflix2.egg-info/requires.txt
pyflix2.egg-info/top_level.txt