Metadata-Version: 1.0
Name: pyflix2
Version: 0.2.1
Summary: A python module for accessing Netflix REST webservice, both V1 and V2 supports oauth and oob.
Home-page: http://pyflix2.readthedocs.org/
Author: Arup Malakar
Author-email: amalakar@gmail.com
License: Copyright (c) 2012, Arup Malakar 
